target_s3tables/__init__.py
target_s3tables/__main__.py
target_s3tables/config.py
target_s3tables/iceberg.py
target_s3tables/sinks.py
target_s3tables/target.py
target_s3tables-0.0.5.dist-info/METADATA
target_s3tables-0.0.5.dist-info/WHEEL
target_s3tables-0.0.5.dist-info/entry_points.txt
target_s3tables-0.0.5.dist-info/licenses/LICENSE
target_s3tables-0.0.5.dist-info/RECORD
