Metadata-Version: 2.4
Name: target-s3tables
Version: 0.0.5
Summary: Singer target for S3Tables, built with the Meltano Singer SDK.
Author-email: Alex Maingot <alex.maingot@gmail.com>
License-Expression: Apache-2.0
License-File: LICENSE
Keywords: ELT,S3Tables
Classifier: Intended Audience :: Developers
Classifier: License :: OSI Approved :: Apache Software License
Classifier: Operating System :: OS Independent
Classifier: Programming Language :: Python :: 3.10
Classifier: Programming Language :: Python :: 3.11
Classifier: Programming Language :: Python :: 3.12
Classifier: Programming Language :: Python :: 3.13
Classifier: Programming Language :: Python :: 3.14
Requires-Python: >=3.10
Requires-Dist: boto3>=1.41.5
Requires-Dist: pyarrow>=15
Requires-Dist: pyiceberg[glue,pyarrow,s3fs]>=0.10.0
Requires-Dist: requests~=2.32.3
Requires-Dist: s3fs~=2025.12.0
Requires-Dist: singer-sdk~=0.53.4
